benchkit/__init__.py
benchkit/data/__init__.py
benchkit/data/datasets.py
benchkit/data/file_saver.py
benchkit/data/helpers.py
benchkit/distributed/__init__.py
benchkit/distributed/accelerate/__init__.py
benchkit/distributed/accelerate/helpers.py
benchkit/distributed/accelerate/tracking/__init__.py
benchkit/distributed/accelerate/tracking/bench_tracker.py
benchkit/misc/__init__.py
benchkit/misc/bench_ascii_logo.txt
benchkit/misc/benchkit.py
benchkit/misc/cli/__init__.py
benchkit/misc/cli/server.py
benchkit/misc/manage.txt
benchkit/misc/requests/__init__.py
benchkit/misc/requests/dataset.py
benchkit/misc/requests/graph.py
benchkit/misc/requests/model_save.py
benchkit/misc/requests/server.py
benchkit/misc/requests/user.py
benchkit/misc/requests/version.py
benchkit/misc/settings.py
benchkit/misc/utils/__init__.py
benchkit/misc/utils/bucket.py
benchkit/misc/utils/tar.py
benchkit/misc/verbose.py
benchkit/nn/__init__.py
benchkit/nn/helpers.py
benchkit/tracking/__init__.py
benchkit/tracking/config.py
benchkit/tracking/graphs/__init__.py
benchkit/tracking/graphs/base_graph.py
benchkit/tracking/graphs/time_series.py
benchkit/tracking/visualizer.py
benchkit/train/__init__.py
benchkit/train/helpers.py
benchkit/train/train_script.txt
benchkit-1.0.2.dist-info/LICENSE
benchkit-1.0.2.dist-info/METADATA
benchkit-1.0.2.dist-info/WHEEL
benchkit-1.0.2.dist-info/entry_points.txt
benchkit-1.0.2.dist-info/RECORD
